bitkub/__init__.py
bitkub/client.py
bitkub/const.py
bitkub/enums.py
bitkub/exception.py
bitkub/models.py
bitkub/validators.py
bitkub_python-0.2.0.dist-info/METADATA
bitkub_python-0.2.0.dist-info/WHEEL
bitkub_python-0.2.0.dist-info/entry_points.txt
bitkub_python-0.2.0.dist-info/licenses/LICENSE
bitkub_python-0.2.0.dist-info/RECORD
