Metadata-Version: 2.1
Name: bitkub-python
Version: 0.2.0
Summary: A Python library for Bitkub API
Author-Email: Praphan Klairith <p.klairith@gmail.com>
Classifier: Programming Language :: Python :: 3
Classifier: License :: OSI Approved :: MIT License
Classifier: Operating System :: OS Independent
Project-URL: Homepage, https://github.com/xbklairith/bitkub-python
Project-URL: Bug Tracker, https://github.com/xbklairith/bitkub-python/issues
Requires-Python: >=3.8
Requires-Dist: requests>=2.31.0
